{"guide_bundles.md":"1dYV30ut","guide_compat.md":"GDzG0yFc","guide_index.md":"v7Ke9fLD","guide_dual-themes.md":"6mnVso9I","guide_load-lang.md":"J73URs_l","guide_load-theme.md":"gTnHfuM4","packages_cli.md":"d5KaBVbS","index.md":"Bwon7sv6","guide_shorthands.md":"9VTL2dBq","languages.md":"QNbN0znj","packages_rehype.md":"tvC6wv5x","packages_markdown-it.md":"kpiGsYLj","packages_monaco.md":"DP1TOoFr","packages_transformers.md":"r6OelAMT","guide_theme-colors.md":"sbEmI7_o","guide_install.md":"Jjr-8iqX","play.md":"vlqPWahS","guide_transformers.md":"TfX6ufNK","themes.md":"SuDTN-fy","packages_twoslash.md":"nL0ACIBB"}
